mpes/__init__.py
mpes/analysis.py
mpes/bandstructure.py
mpes/base.py
mpes/beamtime.py
mpes/dask_tps.py
mpes/fprocessing.py
mpes/igoribw.py
mpes/legacy.py
mpes/mirrorutil.py
mpes/utils.py
mpes/visualization.py
mpes-1.1.4.dist-info/LICENSE.md
mpes-1.1.4.dist-info/METADATA
mpes-1.1.4.dist-info/WHEEL
mpes-1.1.4.dist-info/top_level.txt
mpes-1.1.4.dist-info/RECORD
